iqrfpy/ext/app_helpers/__init__.py
iqrfpy/ext/app_helpers/iqmesh_ntw.py
iqrfpy/ext/app_helpers/iqrf_application.py
iqrfpy/ext/app_helpers/ntw_device.py
iqrfpy/ext/app_helpers/objects.py
iqrfpy/ext/app_helpers/py.typed
iqrfpy/ext/app_helpers/utils.py
iqrfpy_app_helpers-0.1.0.dev2.dist-info/LICENSE
iqrfpy_app_helpers-0.1.0.dev2.dist-info/METADATA
iqrfpy_app_helpers-0.1.0.dev2.dist-info/WHEEL
iqrfpy_app_helpers-0.1.0.dev2.dist-info/top_level.txt
iqrfpy_app_helpers-0.1.0.dev2.dist-info/RECORD
