Metadata-Version: 2.1
Name: iqrfpy-app-helpers
Version: 0.1.0.dev2
Summary: Diagnostics for iqrfpy
Home-page: https://gitlab.iqrf.org/open-source/iqrf-sdk/iqrfpy/iqrfpy-app-helpers
Author: Karel Hanák
Author-email: karel.hanak@iqrf.org
License: Apache-2.0
Project-URL: Homepage, https://gitlab.iqrf.org/open-source/iqrf-sdk/iqrfpy/iqrfpy-app-helpers
Project-URL: Changelog, https://gitlab.iqrf.org/open-source/iqrf-sdk/iqrfpy/iqrfpy-app-helpers/-/blob/master/changelog.md
Project-URL: Source code, https://gitlab.iqrf.org/open-source/iqrf-sdk/iqrfpy/iqrfpy-app-helpers
Project-URL: Issue tracker, https://gitlab.iqrf.org/open-source/iqrf-sdk/iqrfpy/iqrfpy-app-helpers/-/issues
Keywords: iqrf
Classifier: Development Status :: 4 - Beta
Classifier: License :: OSI Approved :: Apache Software License
Classifier: Programming Language :: Python
Classifier: Programming Language :: Python :: 3
Classifier: Programming Language :: Python :: 3.10
Classifier: Programming Language :: Python :: 3.11
Classifier: Programming Language :: Python :: 3.12
Classifier: Operating System :: Microsoft :: Windows
Classifier: Operating System :: POSIX
Classifier: Operating System :: Unix
Classifier: Operating System :: MacOS
Requires-Python: >=3.10
License-File: LICENSE
Requires-Dist: iqrfpy >=0.2.0
Requires-Dist: iqrfpy-mqtt-transport
Requires-Dist: tabulate >=0.9.0
